LICENSE
MANIFEST.in
README.rst
check.py
requirements.txt
setup.py
tox.ini
doc/conf.py
doc/index.rst
doc/intro.rst
doc/_build/html/genindex.html
doc/_build/html/index.html
doc/_build/html/intro.html
doc/_build/html/py-modindex.html
doc/_build/html/search.html
doc/_build/html/pyprocdev/modules.html
doc/_build/html/pyprocdev/pyprocdev._constants.html
doc/_build/html/pyprocdev/pyprocdev._errors.html
doc/_build/html/pyprocdev/pyprocdev._pyprocdev.html
doc/_build/html/pyprocdev/pyprocdev._version.html
doc/_build/html/pyprocdev/pyprocdev.html
doc/_build/html/tests/modules.html
doc/_build/html/tests/tests.html
doc/_build/html/tests/tests.test_procdev.html
doc/pyprocdev/modules.rst
doc/pyprocdev/pyprocdev._constants.rst
doc/pyprocdev/pyprocdev._errors.rst
doc/pyprocdev/pyprocdev._pyprocdev.rst
doc/pyprocdev/pyprocdev._version.rst
doc/pyprocdev/pyprocdev.rst
doc/tests/modules.rst
doc/tests/tests.rst
doc/tests/tests.test_procdev.rst
src/pyprocdev/__init__.py
src/pyprocdev/_constants.py
src/pyprocdev/_errors.py
src/pyprocdev/_pyprocdev.py
src/pyprocdev/_version.py
src/pyprocdev.egg-info/PKG-INFO
src/pyprocdev.egg-info/SOURCES.txt
src/pyprocdev.egg-info/dependency_links.txt
src/pyprocdev.egg-info/requires.txt
src/pyprocdev.egg-info/top_level.txt
tests/__init__.py
tests/test_procdev.py