Metadata-Version: 1.1
Name: pyprocdev
Version: 0.2
Summary: Python interface to /proc/devices
Home-page: UNKNOWN
Author: Anne Mulhern
Author-email: mulhern@cs.wisc.edu
License: GPL 2+
Platform: Linux
Classifier: Development Status :: 2 - Pre-Alpha
Classifier: Intended Audience :: Developers
Classifier: License :: OSI Approved :: GNU General Public License (GPL)
Classifier: Operating System :: POSIX :: Linux
Classifier: Programming Language :: Python
Classifier: Programming Language :: Python :: 2
Classifier: Programming Language :: Python :: 3
Classifier: Programming Language :: Python :: Implementation :: CPython
Classifier: Programming Language :: Python :: Implementation :: PyPy
Classifier: Topic :: Software Development :: Libraries
